LICENSE
MANIFEST.in
README.md
VERSION
setup.cfg
setup.py
src/savage/__init__.py
src/savage/exceptions.py
src/savage/utils.py
src/savage.egg-info/PKG-INFO
src/savage.egg-info/SOURCES.txt
src/savage.egg-info/dependency_links.txt
src/savage.egg-info/requires.txt
src/savage.egg-info/top_level.txt
src/savage/api/__init__.py
src/savage/api/data.py
src/savage/models/__init__.py