Metadata-Version: 2.1
Name: savage
Version: 1.0.0
Summary: Automatic version tracking for SQLAlchemy + PostgreSQL (based on versionalchemy)
Home-page: https://github.com/NerdWalletOSS/savage
Author: Jeremy Lewis
Author-email: jlewis@nerdwallet.com
Maintainer: Jeremy Lewis
Maintainer-email: jlewis@nerdwallet.com
License: MIT License
Download-URL: https://github.com/NerdWalletOSS/savage/archive/v1.0.0.tar.gz
Platform: UNKNOWN
Classifier: Development Status :: 5 - Production/Stable
Classifier: Intended Audience :: Developers
Classifier: License :: OSI Approved :: MIT License
Classifier: Programming Language :: Python
Classifier: Programming Language :: Python :: 2
Classifier: Programming Language :: Python :: 2.7
Classifier: Programming Language :: Python :: 3
Classifier: Programming Language :: Python :: 3.6
Classifier: Programming Language :: Python :: 3.7
Classifier: Programming Language :: SQL
Classifier: Topic :: Database
Classifier: Topic :: Database :: Front-Ends
Classifier: Topic :: Software Development
Classifier: Topic :: Software Development :: Libraries :: Python Modules
Classifier: Operating System :: OS Independent
Requires-Python: >=2.7, !=3.0.*, !=3.1.*, !=3.2.*, !=3.3.*, !=3.4.*, !=3.5.*, <4
Provides-Extra: test
Provides-Extra: dev
